{
    "id": 71,
    "paso":-1,
    "tipo":"instruccionesiniciales",
    "instruccionesejercicio": [
        "La herencia es el proceso de crear nuevas clases a a partir de clases existentes.  La clase que hereda atributos y métodos se conoce como clase base, clase padre o superclase.",
        "En Java, para indicar que una clase hereda de otra se utiliza la palabra clave extends."
    ],
    "opciones": [
        {
            "paso": 0,
            "tipo": "pasoinicial",
            "instruccion": "Paso 1 de 4.  Considera el siguiente código para contestar a la pregunta.  ¿Cómo se le llama a la clase principal de la cual otras clases heredan?",
            "presentacion": [
                "class Deporte {  // <-- a esta clase se le llama: ?",
                "}",
                "class Futbol extends Deporte {",
                "}"
            ],
            "textoEmocional": {
                "neutral": "Inicia con el ejercicio.",                
                "encantado": "Para mover una montaña necesitas comenzar por pequeñas piedras.  ¡Inicia con el ejercicio!",
                "sorprendido": "No permitas que nadie te diga que no puedes conseguir aquello que quieres. ¡Inicia con el ejercicio!",
                "compasivo": "No importa que hoy te equivoques, tienes el resto de tu vida para solucionarlo.  ¡Se que tu puedes!.  Empieza el ejercicio.",
                "esceptico": "Por muy poco que puedas hacer, siempre es más que quedarse de brazos cruzados.  Empieza el ejercicio.",
                "retroalimentacion": {
                    "positiva": "Nadie dijo que la vida fuera fácil ¿pero vas a rendirte ante la primera dificultad?.",
                    "neutral": "La motivación es el mejor método para hacer las cosas.",
                    "negativa": "Rendirse no es la solución, es la escapatorio más fácil."
                }

            },
            "opciones": [
                {
                    "texto": "Superclase o clase padre",
                    "paso": 1,
                    "tipo": "pasooptimo",
                    "instruccion": "Paso 2 de 4.  Considera el siguiente código para contestar a la pregunta. ¿A la clase que hereda de una superclase se le llama?",
                    "presentacion": [
                        "class Deporte {  // <-- a esta clase se le llama: <input type='text' readonly value= 'Superclase o clase padre' class='focusInput'>",
                        "}",
                        "class Futbol extends Deporte { //<-- a esta clase se le llama: ?",
                        "}"
                    ],
                    "textoEmocional": {
                        "neutral": "La respuesta es correcta.  Sigue con el ejercicio",
                        "encantado": "Continua con este entusiasmo.  Ya casi terminas el ejercicio",
                        "sorprendido": "¡Me sorprendes!, noto que cada día eres mejor, continúa con el ejercicio.",
                        "compasivo": "Yo se que tu puedes, ¡sigue adelante!.",
                        "esceptico": "Me parece que tienes una actitud indiferente.  Al menos trata de terminar el ejercicio.",
                        "retroalimentacion": {                            
                            "positiva": "¡Perfecto!.  Sigue con el ejercicio.",
                            "neutral": "La respuesta es correcta.  Sigue con el ejercicio.",
                            "negativa": "¿Estás seguro que se trata de una respuesta razonada?.  Sigue con el ejercicio."                            
                        }
                    },
                    "opciones": [                        
                        {
                            "texto": "Superclase o clase padre",
                            "paso": 2,
                            "tipo": "pasoerroneo",
                            "instruccion": "La respuesta es incorrecta.  La clase derivada (clase hija, subclase) es la clase que agrega y/o especializa el comportamiento a una clase base.  Intenta de nuevo.",
                            "presentacion": [
                                "class Deporte {  // <-- a esta clase se le llama: <input type='text' readonly value= 'Superclase o clase padre' class='focusInput'>",
                                "}",
                                "class Futbol extends Deporte { //<-- a esta clase se le llama: <input type='text' readonly value= 'Superclase o clase padre' class='errorTracing'>",
                                "}"
                            ],
                            "textoEmocional": {
                                "neutral": "La respuesta es incorrecta.  Intenta de nuevo.",
                                "encantado": "Aun cuando la respuesta es incorrecta, se que estás intentando aprender Java.",
                                "sorprendido": "La respuesta no es correcta pero te siento con mucha decisión por aprender Java",
                                "compasivo": "Qué no decaiga tu autoestima, aveces se requiere de tiempo para asimilar los conceptos de Java",
                                "esceptico": "Se que pensabas que este ejercicio ejercicio era muy fácil para ti.",
                                "retroalimentacion": {                           
                                    "positiva": "La respuesta no es la correcta, ¡sigue intentandolo!",
                                    "neutral": "La respuesta no es la correcta",
                                    "negativa": "¿Estás seguro de querer estudiar este curso?."
                        }

                            },
                            "opciones": [                                                                                            
                            ]
                        },
                        {
                            "texto": "Subclase o clase derivada",
                            "paso": 3,
                            "tipo": "pasooptimo",
                            "instruccion": "Paso 3 de 4.  Considera el siguiente código para contestar a la pregunta con verdadero o falso.  ¿Las relaciones de herencia simple forman estructuras jerárquicas tipo árbol?",
                            "presentacion": [
                                "class Deporte {  // <-- superclase de Futbol",
                                "}",
                                "class Futbol extends Deporte { //<-- subclase Deporte y superclase de FutbolPlaya",
                                "}",
                                "class FutbolPlaya extends Futbol { // <-- clase derivada de Futbol",
                                "}"
                            ],
                            "textoEmocional": {
                                "neutral": "La respuesta es correcta.  Continúa con el ejercicio.",
                                "encantado": "Tú entusiasmo hace que aprender sea más fácil.",
                                "sorprendido": "¡Me sorprende tu actitud positiva!, continúa así.",
                                "compasivo": "Con un poco de paciencia vas a mejorar tu aprendizaje con Java, ¡ánimo!.",
                                "esceptico": "Tal vez este ejercicio es fácil para ti pero almenos intenta terminar el ejercicio.",
                                "retroalimentacion": {                            
                                    "positiva": "Por cada esfuerzo, hay una recompensa.  Nunca te rindas. Sigue adelante con el ejercicio.",
                                    "neutral": "La respuesta es correcta.  Continúa con el ejercicio.",
                                    "negativa": "La respuesta es correcta, pero, ¿te lo estas tomando en serio?"                            
                                }
                            },
                            "opciones": [                                 
                                {
                                    "texto": "Verdadero",
                                    "paso": 4,
                                    "tipo": "pasofinaloptimo",
                                    "instruccion": "Paso 4 de 4.  Fin del ejercicio.  ¡Bien hecho!.  Selecciona otro ejercicio del menú.",
                                    "presentacion": [
                                        "class Deporte {  // <-- superclase de Futbol",
                                        "}",
                                        "class Futbol extends Deporte { //<-- subclase Deporte y superclase de FutbolPlaya",
                                        "}",
                                        "class FutbolPlaya extends Futbol { // <-- clase derivada de Futbol",
                                        "}"
                                    ],
                                    "textoEmocional": {
                                        "neutral": "Has finalizado con este ejercicio.",
					"encantado": "En la vida no hay que esperar a que pase la tormenta, hay que aprender a bailar bajo la lluvia, ¡sigue con este entusiasmo!.",              
					"sorprendido": "Cada logro comienza con la decisión de intentarlo, por lo pronto has finalizado con este ejercicio.",
					"compasivo": "Aprender es como remar contra corriente: en cuanto se deja, se retrocede.  ¡continua así!.",                
					"esceptico": "Lo que con mucho trabajo se adquiere, más se ama.  Sigue aprendiendo Java.",
					"retroalimentacion": {
                                            "positiva": "¡Felicidades!.  Has finalizado con este ejercicio.",
                                            "neutral": "Has finalizado con este ejercicio.",
                                            "negativa": "No se puede cambiar lo que te niegas a afrontar.  Al menos llegaste al final del ejercicio."
					}	
                                    },
                                    "opciones": [ ]
                                },
                                {
                                    "texto": "Falso",
                                    "paso": 5,
                                    "tipo": "pasoerroneo",
                                    "instruccion": "La respuesta es incorrecta.  Las relaciones de herencia simple forman estructuras jerárquicas tipo árbol: una superclase existe en una relación jerárquica con sus subclases.  Intentalo de nuevo.",
                                    "presentacion": [
                                        "class Deporte {  // <-- superclase de Futbol",
                                        "}",
                                        "class Futbol extends Deporte { //<-- subclase Deporte y superclase de FutbolPlaya",
                                        "}",
                                        "class FutbolPlaya extends Futbol { // <-- clase derivada de Futbol",
                                        "}"
                                    ],
                                    "textoEmocional": {
                                        "neutral": "La respuesta es incorrecta.  Intenta de nuevo.",
                                        "encantado": "La respuesta no es la correcta pero estoy seguro que vas a encontrar la respuesta correcta.",
                                        "sorprendido": "¡Me gusta tu actitud!, sigue así y estoy seguro que vas a encontrar la respuesta correcta.",
                                        "compasivo": "Me parece que puedes hacerlo mejor, sigue intentándolo.",
                                        "esceptico": "Me preocupa un poco tu indiferencia.  Intenta terminar el ejercicio.",
                                        "retroalimentacion": {                           
                                            "positiva": "Casi, casi, aciertas con la respuesta, ¡sigue intentandolo!",
                                            "neutral": "La respuesta no es la correcta.  Intenta de nuevo.",
                                            "negativa": "La respuesta es incorrecta.  Me siento intranquilo por tu desempeño"
                                        }
                                    },
                                    "opciones": [ ]
                                }                                                                
                            ]
                        },
                        {
                            "texto": "Superclase o subclase",
                            "paso": 6,
                            "tipo": "pasoerroneo",
                            "instruccion": "La respuesta es incorrecta.  La clase derivada (clase hija, subclase) es la clase que agrega y/o especializa el comportamiento a una clase base.  Intenta de nuevo.",
                            "presentacion": [
                                "class Deporte {  // <-- a esta clase se le llama: <input type='text' readonly value= 'Superclase o clase padre' class='focusInput'>",
                                "}",
                                "class Futbol extends Deporte { //<-- a esta clase se le llama: <input type='text' readonly value= 'Superclase o subclase' class='errorTracing'>",
                                "}"
                            ],
                            "textoEmocional": {
                                "neutral": "La respuesta es incorrecta.  Intenta de nuevo.",
                                "encantado": "La respuesta no es la correcta pero estoy seguro que vas a encontrar la respuesta correcta.",
                                "sorprendido": "¡Me gusta tu actitud!, sigue así y estoy seguro que vas a encontrar la respuesta correcta.",
                                "compasivo": "Me parece que puedes hacerlo mejor, sigue intentándolo.",
                                "esceptico": "Me preocupa un poco tu indiferencia.  Intenta terminar el ejercicio.",
                                "retroalimentacion": {                           
                                    "positiva": "Por cada esfuerzo, hay una recompensa.  Nunca te rindas. Sigue adelante con el ejercicio.",
                                    "neutral": "La respuesta no es la correcta.  Intenta de nuevo.",
                                    "negativa": "La respuesta es incorrecta.  Necesitas mejorar."
                                }
                            },
                            "opciones": []
                        },
                        {
                            "texto": "Ninguna de las anteriores",
                            "paso": 7,
                            "tipo": "paserroneo",
                            "instruccion": "La respuesta es incorrecta.  La clase derivada (clase hija, subclase) es la clase que agrega y/o especializa el comportamiento a una clase base.  Intenta de nuevo.",
                            "presentacion": [
                                "class Deporte {  // <-- a esta clase se le llama: <input type='text' readonly value= 'Superclase o clase padre' class='focusInput'>",
                                "}",
                                "class Futbol extends Deporte { //<-- a esta clase se le llama: <input type='text' readonly value= 'Ninguna de las anteriores' class='errorTracing'>",
                                "}"
                            ],
                            "textoEmocional": {
                                "neutral": "La respuesta es incorrecta.  Intenta de nuevo.",
                                "encantado": "Aun cuando la respuesta es incorrecta, se que estás intentando aprender Java.",
                                "sorprendido": "La respuesta no es correcta pero te siento con mucha decisión por aprender Java",
                                "compasivo": "Qué no decaiga tu autoestima, aveces se requiere de tiempo para asimilar los conceptos de Java",
                                "esceptico": "Se que pensabas que este ejercicio ejercicio era muy fácil para ti.",
                                "retroalimentacion": {                           
                                    "positiva": "¡Intentalo una vez más!",
                                    "neutral": "La respuesta es incorrecta.  Intenta de nuevo.",
                                    "negativa": "Creo que no has estudiado lo suficiente."
                                }
                            },
                            "opciones": []
                        }
                        
                    ]
                },
                {
                    "texto": "Subclase o clase derivada",
                    "paso": 8,
                    "tipo": "pasoerroneo",
                    "instruccion":  "La respuesta es incorrecta.  La clase derivada (clase hija, subclase) es la clase que agrega y/o especializa el comportamiento a una clase base.  Intenta de nuevo.",
                    "presentacion": [
                        "class Deporte {  // <-- a esta clase se le llama: <input type='text' readonly value= 'Subclase o clase derivada' class='errorTracing'>",
                        "}",
                        "class Futbol extends Deporte {",
                        "}"
                    ],
                    "textoEmocional": {
                         "neutral": "La respuesta es incorrecta.  Sigue con el ejercicio",
                        "encantado": "Continua con este entusiasmo y veras que todos tus sueños mañana se harán realidad.",
                        "sorprendido": "¡Me sorprendes!, noto que cada día eres mejor, continúa así.",
                        "compasivo": "Yo se que eres buen estudiante, ¡sigue adelante!.",
                        "esceptico": "Una persona que estudia jamás será un fracasado.  Trata de terminar el ejercicio.",
                        "retroalimentacion": {                            
                            "positiva": "¡Lo has hecho muy bien!.  Sigue con el ejercicio.",
                            "neutral": "La respuesta es incorrecta.  Sigue con el ejercicio.",
                            "negativa": "¿Estás seguro que se trata de una respuesta razonada?"  
                        }
                    },
                    "opciones": [
                    ]
                },
                {
                    "texto": "Superclase o subclase",
                    "paso": 9,
                    "tipo": "pasoerroneo",
                    "instruccion":  "La respuesta es incorrecta.  La clase derivada (clase hija, subclase) es la clase que agrega y/o especializa el comportamiento a una clase base.  Intenta de nuevo.",
                    "presentacion": [
                        "class Deporte {  // <-- a esta clase se le llama: <input type='text' readonly value= 'Superclase o subclase' class='errorTracing'>",
                        "}",
                        "class Futbol extends Deporte {",
                        "}"
                    ],
                    "textoEmocional": {
                        "neutral": "La respuesta es incorrecta.  Sigue con el ejercicio",
                        "encantado": "Para estudiar hay que tener perseverancia, paciencia y motivación.  ¡Sigue así!",
                        "sorprendido": "¡Me sorprendes!, la respuesta no es correcta pero no pierdas esa actitud por aprender.",
                        "compasivo": "Estudiar Java demanda tiempo y esfuerzo pero al final siempre hay resultados positivos, ¡ánimo!.",
                        "esceptico": "Una persona que estudia jamás será un fracasado.  Trata de terminar el ejercicio.",
                        "retroalimentacion": {                            
                            "positiva": "¡Casi casi!.  La respuesta es incorrecta.  Continúa con el ejercicio.",
                            "neutral": "La respuesta es incorrecta.  Sigue con el ejercicio.",
                            "negativa": "La respuesta es incorrecta, sin embargo, ¿estás seguro que se trata de una respuesta razonada?"                            
                        }
                    },
                    "opciones": [
                    ]
                },
                {
                    "texto": "Ninguna de las anteriores",
                    "paso": 10,
                    "tipo": "pasoerroneo",
                    "instruccion":  "La respuesta es incorrecta.  La clase derivada (clase hija, subclase) es la clase que agrega y/o especializa el comportamiento a una clase base.  Intenta de nuevo.",
                    "presentacion": [
                        "class Deporte {  // <-- a esta clase se le llama: <input type='text' readonly value= 'Ninguna de las anteriores' class='errorTracing'>",
                        "}",
                        "class Futbol extends Deporte {",
                        "}"
                    ],
                    "textoEmocional": {
                        "neutral": "La respuesta es incorrecta.  Intenta de nuevo.",
                        "encantado": "Aun cuando la respuesta es incorrecta, se que estás intentando aprender Java.",
                        "sorprendido": "La respuesta no es correcta pero te siento con mucha decisión por aprender Java",
                        "compasivo": "Todos tenemos una habilidad distinta y cada día aprendemos un poquito más, tú eres una persona triunfadora.",
                        "esceptico": "No desperdicies tu talento sin hacer nada productivo, estudia y sácale provecho a tus habilidades.",
                        "retroalimentacion": {                           
                            "positiva": "Casi, casi, ¡Intentalo de nuevo!",
                            "neutral": "La respuesta es incorrecta.  Intenta de nuevo.",
                            "negativa": "Creo que no has estudiado lo suficiente."
                        }
                    },
                    "opciones": [
                    ]
                }
            ]
        }
    ]
}