{
    "id":58,
    "paso":-1,
    "instruccionesejercicio": 
    [
        "Después de que el arreglo ha sido creado, se puede utilizar la variable de acuerdo al índice, como si fuera una variable regular.",
        "Por ejemplo: miLista[2] = miLista[0] + miLista[1];"
    ],
    "opciones": 
    [
        {
            "paso": 0,
            "tipo": "pasoinicial",
            "instruccion": "¿Qué se imprime en la consola de salida al ejecutar el siguiente programa?",
            "presentacion": 
            [
                "public class Arreglos {",
                "\tpublic static void main( String args[] ){",
                "\t\tboolean[] b = new boolean[2];",
                "\t\tdouble[] d = new double[2];",
                "\t\tSystem.out.print( b[0] );",
                "\t\tSystem.out.println( d[1] );",
                "\t}",
                "}"
            ],
            "textoEmocional": {
                "neutral": "Inicia el ejercicio para continuar con el curso.",
                "encantado": "Da siempre lo mejor que tienes. Lo que plantes ahora, lo cosecharás más tarde.  Comienza con el ejercicio.",              
                "sorprendido": "La determinación es el punto inicial de todo logro.  Inicia con el ejercicio.",
                "compasivo": "La derrota no es el peor de los fracasos. No intentarlo es el verdadero fracaso.  Intenta resolver el ejercicio.",                
                "esceptico": "Si el mundo te parece frío, enciende fuego para calentarlo.  Inicia con el ejercicio.",
                "retroalimentacion": {
                    "positiva": "La única forma de hacer un gran trabajo es amar lo que haces.",
                    "neutral": "La disciplina es el puente entre metas y logros.",
                    "negativa": "La fortuna favorece al valiente."
                } 
           },
            "opciones": 
            [
                {
                    "texto": "true0",
                    "paso": 1,
                    "tipo": "pasoerroneo",
                    "instruccion": "La respuesta es incorrecta.  Intenta de nuevo.",
                    "presentacion": 
                    [
                        "public class Arreglos {",
                        "\tpublic static void main( String args[] ){",
                        "\t\tboolean[] b = new boolean[2];",
                        "\t\tdouble[] d = new double[2];",
                        "\t\tSystem.out.print( b[0] );",
                        "\t\tSystem.out.println( d[1] );",
                        "\t}",
                        "}"
                    ],
                    "textoEmocional":
                    {
                        "neutral":"Inicia los ejercicios",
                        "encantado":"Estas muy bien, inicia con el ejercicio",
                        "sorprendido":"Wow, me sorprende el momento que pasas, inicia con el ejercicio",
                        "compasivo":"Se que has sentido que no progresas del todo bien, pero mejoraras, realiza el ejercicio",
                        "esceptico":"No creo que este ejercicio sea adecuado para ti, piensa si quieres iniciar este ejercicio",
                        "retroalimentacion":
                        {
                            "positiva":"No importa el error vas muy bien",
                            "neutral":"Sigue asi, continua",
                            "negativa":"Creo que no lo tienes claro aun, deberias considerar mirar alguna de mis recomendaciones"
                        }
                    },
                    "opciones": []
                },
                {
                    "texto": "false0",
                    "paso": 2,
                    "tipo": "pasoerroneo",
                    "instruccion": "La respuesta es incorrecta.  Intenta de nuevo.",
                    "presentacion": 
                    [
                        "public class Arreglos {",
                        "\tpublic static void main( String args[] ){",
                        "\t\tboolean[] b = new boolean[2];",
                        "\t\tdouble[] d = new double[2];",
                        "\t\tSystem.out.print( b[0] );",
                        "\t\tSystem.out.println( d[1] );",
                        "\t}",
                        "}"
                    ],
                    "textoEmocional":
                    {
                        "neutral":"Inicia los ejercicios",
                        "encantado":"Estas muy bien, inicia con el ejercicio",
                        "sorprendido":"Wow, me sorprende el momento que pasas, inicia con el ejercicio",
                        "compasivo":"Se que has sentido que no progresas del todo bien, pero mejoraras, realiza el ejercicio",
                        "esceptico":"No creo que este ejercicio sea adecuado para ti, piensa si quieres iniciar este ejercicio",
                        "retroalimentacion":
                        {
                            "positiva":"No importa el error vas muy bien",
                            "neutral":"Sigue asi, continua",
                            "negativa":"Creo que no lo tienes claro aun, deberias considerar mirar alguna de mis recomendaciones"
                        }
                    },
                    "opciones": []
                },    
                {
                    "texto": "true0.0",
                    "paso": 3,
                    "tipo": "pasoerroneo",
                    "instruccion": "La respuesta es incorrecta.  Intenta de nuevo.",
                    "presentacion": 
                    [
                        "public class Arreglos {",
                        "\tpublic static void main( String args[] ){",
                        "\t\tboolean[] b = new boolean[2];",
                        "\t\tdouble[] d = new double[2];",
                        "\t\tSystem.out.print( b[0] );",
                        "\t\tSystem.out.println( d[1] );",
                        "\t}",
                        "}"
                    ],
                    "textoEmocional":
                    {
                        "neutral":"Inicia los ejercicios",
                        "encantado":"Estas muy bien, inicia con el ejercicio",
                        "sorprendido":"Wow, me sorprende el momento que pasas, inicia con el ejercicio",
                        "compasivo":"Se que has sentido que no progresas del todo bien, pero mejoraras, realiza el ejercicio",
                        "esceptico":"No creo que este ejercicio sea adecuado para ti, piensa si quieres iniciar este ejercicio",
                        "retroalimentacion":
                        {
                            "positiva":"No importa el error vas muy bien",
                            "neutral":"Sigue asi, continua",
                            "negativa":"Creo que no lo tienes claro aun, deberias considerar mirar alguna de mis recomendaciones"
                        }
                    },
                    "opciones": []
                },                
                {
                    "texto": "false0.0",
                    "paso": 4,
                    "tipo": "pasofinaloptimo",
                    "instruccion": "La respuesta es correcta.",
                    "presentacion": 
                    [
                        "public class Arreglos {",
                        "\tpublic static void main( String args[] ){",
                        "\t\tboolean[] b = new boolean[2];",
                        "\t\tdouble[] d = new double[2];",
                        "\t\tSystem.out.print( b[0] );",
                        "\t\tSystem.out.println( d[1] );",
                        "\t}",
                        "}"
                    ],
                    "textoEmocional":
                    {
                        "neutral":"Inicia los ejercicios",
                        "encantado":"Estas muy bien, inicia con el ejercicio",
                        "sorprendido":"Wow, me sorprende el momento que pasas, inicia con el ejercicio",
                        "compasivo":"Se que has sentido que no progresas del todo bien, pero mejoraras, realiza el ejercicio",
                        "esceptico":"No creo que este ejercicio sea adecuado para ti, piensa si quieres iniciar este ejercicio",
                        "retroalimentacion":
                        {
                            "positiva":"No importa el error vas muy bien",
                            "neutral":"Sigue asi, continua",
                            "negativa":"Creo que no lo tienes claro aun, deberias considerar mirar alguna de mis recomendaciones"
                        }
                    },
                    "opciones": []
                }
            ]
        }
    ] 
}